[
  {
    "line": 1,
    "elements": [
      {
        "line": 25,
        "name": "To Validate the Registration Form",
        "description": "",
        "id": "to-validate-the-softound-challenge;to-validate-the-registration-form;;2",
        "type": "scenario",
        "keyword": "Scenario Outline",
        "steps": [
          {
            "result": {
              "duration": 1649697000,
              "status": "passed"
            },
            "line": 5,
            "name": ": launch the browser",
            "match": {
              "location": "Chall.launch_the_browser()"
            },
            "keyword": "Given "
          },
          {
            "result": {
              "duration": 3251619100,
              "status": "passed"
            },
            "line": 7,
            "name": "launch the Softound Url",
            "match": {
              "location": "Chall.launch_the_Softound_Url()"
            },
            "keyword": "When "
          },
          {
            "result": {
              "duration": 77782700,
              "status": "passed"
            },
            "line": 9,
            "name": "Enter the \"Jayapriya\"FirstName",
            "match": {
              "arguments": [
                {
                  "val": "\"Jayapriya\"",
                  "offset": 10
                }
              ],
              "location": "Chall.enter_the_FirstName(String)"
            },
            "keyword": "Then "
          },
          {
            "result": {
              "duration": 56275000,
              "status": "passed"
            },
            "line": 11,
            "name": "Enter the \"s\"LastName",
            "match": {
              "arguments": [
                {
                  "val": "\"s\"",
                  "offset": 10
                }
              ],
              "location": "Chall.enter_the_LastName(String)"
            },
            "keyword": "And "
          },
          {
            "result": {
              "duration": 75655000,
              "status": "passed"
            },
            "line": 13,
            "name": "Enter the \"sr.jpriya@gmail.com\"EmailAddress",
            "match": {
              "arguments": [
                {
                  "val": "\"sr.jpriya@gmail.com\"",
                  "offset": 10
                }
              ],
              "location": "Chall.enter_the_EmailAddress(String)"
            },
            "keyword": "And "
          },
          {
            "result": {
              "duration": 557978800,
              "status": "passed"
            },
            "line": 15,
            "name": "select Your \"29.05.2020\"BirthDate",
            "match": {
              "arguments": [
                {
                  "val": "\"29.05.2020\"",
                  "offset": 12
                }
              ],
              "location": "Chall.select_Your_BirthDate(String)"
            },
            "keyword": "And "
          },
          {
            "result": {
              "duration": 310704400,
              "status": "passed"
            },
            "line": 17,
            "name": "click SubmitButton",
            "match": {
              "location": "Chall.click_SubmitButton()"
            },
            "keyword": "And "
          },
          {
            "result": {
              "duration": 57670000,
              "status": "passed"
            },
            "line": 19,
            "name": "Print The Submission Message",
            "match": {
              "location": "Chall.print_The_Submission_Message()"
            },
            "keyword": "And "
          },
          {
            "result": {
              "duration": 3190188200,
              "status": "passed"
            },
            "line": 21,
            "name": "close the Browser",
            "match": {
              "location": "Chall.close_the_Browser()"
            },
            "keyword": "Then "
          }
        ]
      },
      {
        "line": 26,
        "name": "To Validate the Registration Form",
        "description": "",
        "id": "to-validate-the-softound-challenge;to-validate-the-registration-form;;3",
        "type": "scenario",
        "keyword": "Scenario Outline",
        "steps": [
          {
            "result": {
              "duration": 875863100,
              "status": "passed"
            },
            "line": 5,
            "name": ": launch the browser",
            "match": {
              "location": "Chall.launch_the_browser()"
            },
            "keyword": "Given "
          },
          {
            "result": {
              "duration": 2668632400,
              "status": "passed"
            },
            "line": 7,
            "name": "launch the Softound Url",
            "match": {
              "location": "Chall.launch_the_Softound_Url()"
            },
            "keyword": "When "
          },
          {
            "result": {
              "duration": 64704200,
              "status": "passed"
            },
            "line": 9,
            "name": "Enter the \"s\"FirstName",
            "match": {
              "arguments": [
                {
                  "val": "\"s\"",
                  "offset": 10
                }
              ],
              "location": "Chall.enter_the_FirstName(String)"
            },
            "keyword": "Then "
          },
          {
            "result": {
              "duration": 68085400,
              "status": "passed"
            },
            "line": 11,
            "name": "Enter the \"Jayapriya\"LastName",
            "match": {
              "arguments": [
                {
                  "val": "\"Jayapriya\"",
                  "offset": 10
                }
              ],
              "location": "Chall.enter_the_LastName(String)"
            },
            "keyword": "And "
          },
          {
            "result": {
              "duration": 69013900,
              "status": "passed"
            },
            "line": 13,
            "name": "Enter the \"sr.jpriya@gmail.com\"EmailAddress",
            "match": {
              "arguments": [
                {
                  "val": "\"sr.jpriya@gmail.com\"",
                  "offset": 10
                }
              ],
              "location": "Chall.enter_the_EmailAddress(String)"
            },
            "keyword": "And "
          },
          {
            "result": {
              "duration": 563469700,
              "status": "passed"
            },
            "line": 15,
            "name": "select Your \"29.05.199\"BirthDate",
            "match": {
              "arguments": [
                {
                  "val": "\"29.05.199\"",
                  "offset": 12
                }
              ],
              "location": "Chall.select_Your_BirthDate(String)"
            },
            "keyword": "And "
          },
          {
            "result": {
              "duration": 341620400,
              "status": "passed"
            },
            "line": 17,
            "name": "click SubmitButton",
            "match": {
              "location": "Chall.click_SubmitButton()"
            },
            "keyword": "And "
          },
          {
            "result": {
              "duration": 33880900,
              "status": "passed"
            },
            "line": 19,
            "name": "Print The Submission Message",
            "match": {
              "location": "Chall.print_The_Submission_Message()"
            },
            "keyword": "And "
          },
          {
            "result": {
              "duration": 3119010300,
              "status": "passed"
            },
            "line": 21,
            "name": "close the Browser",
            "match": {
              "location": "Chall.close_the_Browser()"
            },
            "keyword": "Then "
          }
        ]
      },
      {
        "line": 27,
        "name": "To Validate the Registration Form",
        "description": "",
        "id": "to-validate-the-softound-challenge;to-validate-the-registration-form;;4",
        "type": "scenario",
        "keyword": "Scenario Outline",
        "steps": [
          {
            "result": {
              "duration": 809762200,
              "status": "passed"
            },
            "line": 5,
            "name": ": launch the browser",
            "match": {
              "location": "Chall.launch_the_browser()"
            },
            "keyword": "Given "
          },
          {
            "result": {
              "duration": 1947221700,
              "status": "passed"
            },
            "line": 7,
            "name": "launch the Softound Url",
            "match": {
              "location": "Chall.launch_the_Softound_Url()"
            },
            "keyword": "When "
          },
          {
            "result": {
              "duration": 68825000,
              "status": "passed"
            },
            "line": 9,
            "name": "Enter the \"Jayapriya\"FirstName",
            "match": {
              "arguments": [
                {
                  "val": "\"Jayapriya\"",
                  "offset": 10
                }
              ],
              "location": "Chall.enter_the_FirstName(String)"
            },
            "keyword": "Then "
          },
          {
            "result": {
              "duration": 58491800,
              "status": "passed"
            },
            "line": 11,
            "name": "Enter the \"s\"LastName",
            "match": {
              "arguments": [
                {
                  "val": "\"s\"",
                  "offset": 10
                }
              ],
              "location": "Chall.enter_the_LastName(String)"
            },
            "keyword": "And "
          },
          {
            "result": {
              "duration": 60494700,
              "status": "passed"
            },
            "line": 13,
            "name": "Enter the \"sr.jpriya\"EmailAddress",
            "match": {
              "arguments": [
                {
                  "val": "\"sr.jpriya\"",
                  "offset": 10
                }
              ],
              "location": "Chall.enter_the_EmailAddress(String)"
            },
            "keyword": "And "
          },
          {
            "result": {
              "duration": 558140300,
              "status": "passed"
            },
            "line": 15,
            "name": "select Your \"29.05.2003\"BirthDate",
            "match": {
              "arguments": [
                {
                  "val": "\"29.05.2003\"",
                  "offset": 12
                }
              ],
              "location": "Chall.select_Your_BirthDate(String)"
            },
            "keyword": "And "
          },
          {
            "result": {
              "duration": 295344300,
              "status": "passed"
            },
            "line": 17,
            "name": "click SubmitButton",
            "match": {
              "location": "Chall.click_SubmitButton()"
            },
            "keyword": "And "
          },
          {
            "result": {
              "duration": 39727800,
              "status": "passed"
            },
            "line": 19,
            "name": "Print The Submission Message",
            "match": {
              "location": "Chall.print_The_Submission_Message()"
            },
            "keyword": "And "
          },
          {
            "result": {
              "duration": 3117311600,
              "status": "passed"
            },
            "line": 21,
            "name": "close the Browser",
            "match": {
              "location": "Chall.close_the_Browser()"
            },
            "keyword": "Then "
          }
        ]
      },
      {
        "line": 28,
        "name": "To Validate the Registration Form",
        "description": "",
        "id": "to-validate-the-softound-challenge;to-validate-the-registration-form;;5",
        "type": "scenario",
        "keyword": "Scenario Outline",
        "steps": [
          {
            "result": {
              "duration": 910689200,
              "status": "passed"
            },
            "line": 5,
            "name": ": launch the browser",
            "match": {
              "location": "Chall.launch_the_browser()"
            },
            "keyword": "Given "
          },
          {
            "result": {
              "duration": 2006681100,
              "status": "passed"
            },
            "line": 7,
            "name": "launch the Softound Url",
            "match": {
              "location": "Chall.launch_the_Softound_Url()"
            },
            "keyword": "When "
          },
          {
            "result": {
              "duration": 61063600,
              "status": "passed"
            },
            "line": 9,
            "name": "Enter the \"Jayapriya\"FirstName",
            "match": {
              "arguments": [
                {
                  "val": "\"Jayapriya\"",
                  "offset": 10
                }
              ],
              "location": "Chall.enter_the_FirstName(String)"
            },
            "keyword": "Then "
          },
          {
            "result": {
              "duration": 56955000,
              "status": "passed"
            },
            "line": 11,
            "name": "Enter the \"s\"LastName",
            "match": {
              "arguments": [
                {
                  "val": "\"s\"",
                  "offset": 10
                }
              ],
              "location": "Chall.enter_the_LastName(String)"
            },
            "keyword": "And "
          },
          {
            "result": {
              "duration": 71209600,
              "status": "passed"
            },
            "line": 13,
            "name": "Enter the \"sr.jpriya@gmail.com\"EmailAddress",
            "match": {
              "arguments": [
                {
                  "val": "\"sr.jpriya@gmail.com\"",
                  "offset": 10
                }
              ],
              "location": "Chall.enter_the_EmailAddress(String)"
            },
            "keyword": "And "
          },
          {
            "result": {
              "duration": 558413300,
              "status": "passed"
            },
            "line": 15,
            "name": "select Your \"29.05.2025\"BirthDate",
            "match": {
              "arguments": [
                {
                  "val": "\"29.05.2025\"",
                  "offset": 12
                }
              ],
              "location": "Chall.select_Your_BirthDate(String)"
            },
            "keyword": "And "
          },
          {
            "result": {
              "duration": 274495500,
              "status": "passed"
            },
            "line": 17,
            "name": "click SubmitButton",
            "match": {
              "location": "Chall.click_SubmitButton()"
            },
            "keyword": "And "
          },
          {
            "result": {
              "duration": 34593200,
              "status": "passed"
            },
            "line": 19,
            "name": "Print The Submission Message",
            "match": {
              "location": "Chall.print_The_Submission_Message()"
            },
            "keyword": "And "
          },
          {
            "result": {
              "duration": 3199203100,
              "status": "passed"
            },
            "line": 21,
            "name": "close the Browser",
            "match": {
              "location": "Chall.close_the_Browser()"
            },
            "keyword": "Then "
          }
        ]
      },
      {
        "line": 29,
        "name": "To Validate the Registration Form",
        "description": "",
        "id": "to-validate-the-softound-challenge;to-validate-the-registration-form;;6",
        "type": "scenario",
        "keyword": "Scenario Outline",
        "steps": [
          {
            "result": {
              "duration": 901177300,
              "status": "passed"
            },
            "line": 5,
            "name": ": launch the browser",
            "match": {
              "location": "Chall.launch_the_browser()"
            },
            "keyword": "Given "
          },
          {
            "result": {
              "duration": 2204499400,
              "status": "passed"
            },
            "line": 7,
            "name": "launch the Softound Url",
            "match": {
              "location": "Chall.launch_the_Softound_Url()"
            },
            "keyword": "When "
          },
          {
            "result": {
              "duration": 63748800,
              "status": "passed"
            },
            "line": 9,
            "name": "Enter the \"Jayapriya\"FirstName",
            "match": {
              "arguments": [
                {
                  "val": "\"Jayapriya\"",
                  "offset": 10
                }
              ],
              "location": "Chall.enter_the_FirstName(String)"
            },
            "keyword": "Then "
          },
          {
            "result": {
              "duration": 56066600,
              "status": "passed"
            },
            "line": 11,
            "name": "Enter the \"s\"LastName",
            "match": {
              "arguments": [
                {
                  "val": "\"s\"",
                  "offset": 10
                }
              ],
              "location": "Chall.enter_the_LastName(String)"
            },
            "keyword": "And "
          },
          {
            "result": {
              "duration": 63291300,
              "status": "passed"
            },
            "line": 13,
            "name": "Enter the \"12345\"EmailAddress",
            "match": {
              "arguments": [
                {
                  "val": "\"12345\"",
                  "offset": 10
                }
              ],
              "location": "Chall.enter_the_EmailAddress(String)"
            },
            "keyword": "And "
          },
          {
            "result": {
              "duration": 561553600,
              "status": "passed"
            },
            "line": 15,
            "name": "select Your \"29.05.2013\"BirthDate",
            "match": {
              "arguments": [
                {
                  "val": "\"29.05.2013\"",
                  "offset": 12
                }
              ],
              "location": "Chall.select_Your_BirthDate(String)"
            },
            "keyword": "And "
          },
          {
            "result": {
              "duration": 316355900,
              "status": "passed"
            },
            "line": 17,
            "name": "click SubmitButton",
            "match": {
              "location": "Chall.click_SubmitButton()"
            },
            "keyword": "And "
          },
          {
            "result": {
              "duration": 36101800,
              "status": "passed"
            },
            "line": 19,
            "name": "Print The Submission Message",
            "match": {
              "location": "Chall.print_The_Submission_Message()"
            },
            "keyword": "And "
          },
          {
            "result": {
              "duration": 3142814500,
              "status": "passed"
            },
            "line": 21,
            "name": "close the Browser",
            "match": {
              "location": "Chall.close_the_Browser()"
            },
            "keyword": "Then "
          }
        ]
      },
      {
        "line": 30,
        "name": "To Validate the Registration Form",
        "description": "",
        "id": "to-validate-the-softound-challenge;to-validate-the-registration-form;;7",
        "type": "scenario",
        "keyword": "Scenario Outline",
        "steps": [
          {
            "result": {
              "duration": 839625900,
              "status": "passed"
            },
            "line": 5,
            "name": ": launch the browser",
            "match": {
              "location": "Chall.launch_the_browser()"
            },
            "keyword": "Given "
          },
          {
            "result": {
              "duration": 3030734000,
              "status": "passed"
            },
            "line": 7,
            "name": "launch the Softound Url",
            "match": {
              "location": "Chall.launch_the_Softound_Url()"
            },
            "keyword": "When "
          },
          {
            "result": {
              "duration": 76179600,
              "status": "passed"
            },
            "line": 9,
            "name": "Enter the \"Jayapriya\"FirstName",
            "match": {
              "arguments": [
                {
                  "val": "\"Jayapriya\"",
                  "offset": 10
                }
              ],
              "location": "Chall.enter_the_FirstName(String)"
            },
            "keyword": "Then "
          },
          {
            "result": {
              "duration": 66871300,
              "status": "passed"
            },
            "line": 11,
            "name": "Enter the \"123125\"LastName",
            "match": {
              "arguments": [
                {
                  "val": "\"123125\"",
                  "offset": 10
                }
              ],
              "location": "Chall.enter_the_LastName(String)"
            },
            "keyword": "And "
          },
          {
            "result": {
              "duration": 80738300,
              "status": "passed"
            },
            "line": 13,
            "name": "Enter the \"sr.jpriya@gmail.com\"EmailAddress",
            "match": {
              "arguments": [
                {
                  "val": "\"sr.jpriya@gmail.com\"",
                  "offset": 10
                }
              ],
              "location": "Chall.enter_the_EmailAddress(String)"
            },
            "keyword": "And "
          },
          {
            "result": {
              "duration": 562327200,
              "status": "passed"
            },
            "line": 15,
            "name": "select Your \"50.05.1000\"BirthDate",
            "match": {
              "arguments": [
                {
                  "val": "\"50.05.1000\"",
                  "offset": 12
                }
              ],
              "location": "Chall.select_Your_BirthDate(String)"
            },
            "keyword": "And "
          },
          {
            "result": {
              "duration": 258376400,
              "status": "passed"
            },
            "line": 17,
            "name": "click SubmitButton",
            "match": {
              "location": "Chall.click_SubmitButton()"
            },
            "keyword": "And "
          },
          {
            "result": {
              "duration": 46238000,
              "status": "passed"
            },
            "line": 19,
            "name": "Print The Submission Message",
            "match": {
              "location": "Chall.print_The_Submission_Message()"
            },
            "keyword": "And "
          },
          {
            "result": {
              "duration": 3095163300,
              "status": "passed"
            },
            "line": 21,
            "name": "close the Browser",
            "match": {
              "location": "Chall.close_the_Browser()"
            },
            "keyword": "Then "
          }
        ]
      },
      {
        "line": 31,
        "name": "To Validate the Registration Form",
        "description": "",
        "id": "to-validate-the-softound-challenge;to-validate-the-registration-form;;8",
        "type": "scenario",
        "keyword": "Scenario Outline",
        "steps": [
          {
            "result": {
              "duration": 865499200,
              "status": "passed"
            },
            "line": 5,
            "name": ": launch the browser",
            "match": {
              "location": "Chall.launch_the_browser()"
            },
            "keyword": "Given "
          },
          {
            "result": {
              "duration": 2277554700,
              "status": "passed"
            },
            "line": 7,
            "name": "launch the Softound Url",
            "match": {
              "location": "Chall.launch_the_Softound_Url()"
            },
            "keyword": "When "
          },
          {
            "result": {
              "duration": 66672100,
              "status": "passed"
            },
            "line": 9,
            "name": "Enter the \"123987\"FirstName",
            "match": {
              "arguments": [
                {
                  "val": "\"123987\"",
                  "offset": 10
                }
              ],
              "location": "Chall.enter_the_FirstName(String)"
            },
            "keyword": "Then "
          },
          {
            "result": {
              "duration": 53273100,
              "status": "passed"
            },
            "line": 11,
            "name": "Enter the \"s\"LastName",
            "match": {
              "arguments": [
                {
                  "val": "\"s\"",
                  "offset": 10
                }
              ],
              "location": "Chall.enter_the_LastName(String)"
            },
            "keyword": "And "
          },
          {
            "result": {
              "duration": 69898700,
              "status": "passed"
            },
            "line": 13,
            "name": "Enter the \"sr.jpriya@gmail.com\"EmailAddress",
            "match": {
              "arguments": [
                {
                  "val": "\"sr.jpriya@gmail.com\"",
                  "offset": 10
                }
              ],
              "location": "Chall.enter_the_EmailAddress(String)"
            },
            "keyword": "And "
          },
          {
            "result": {
              "duration": 560654600,
              "status": "passed"
            },
            "line": 15,
            "name": "select Your \"29.15.1993\"BirthDate",
            "match": {
              "arguments": [
                {
                  "val": "\"29.15.1993\"",
                  "offset": 12
                }
              ],
              "location": "Chall.select_Your_BirthDate(String)"
            },
            "keyword": "And "
          },
          {
            "result": {
              "duration": 291286900,
              "status": "passed"
            },
            "line": 17,
            "name": "click SubmitButton",
            "match": {
              "location": "Chall.click_SubmitButton()"
            },
            "keyword": "And "
          },
          {
            "result": {
              "duration": 33257200,
              "status": "passed"
            },
            "line": 19,
            "name": "Print The Submission Message",
            "match": {
              "location": "Chall.print_The_Submission_Message()"
            },
            "keyword": "And "
          },
          {
            "result": {
              "duration": 3155381600,
              "status": "passed"
            },
            "line": 21,
            "name": "close the Browser",
            "match": {
              "location": "Chall.close_the_Browser()"
            },
            "keyword": "Then "
          }
        ]
      },
      {
        "line": 32,
        "name": "To Validate the Registration Form",
        "description": "",
        "id": "to-validate-the-softound-challenge;to-validate-the-registration-form;;9",
        "type": "scenario",
        "keyword": "Scenario Outline",
        "steps": [
          {
            "result": {
              "duration": 877811900,
              "status": "passed"
            },
            "line": 5,
            "name": ": launch the browser",
            "match": {
              "location": "Chall.launch_the_browser()"
            },
            "keyword": "Given "
          },
          {
            "result": {
              "duration": 2086380800,
              "status": "passed"
            },
            "line": 7,
            "name": "launch the Softound Url",
            "match": {
              "location": "Chall.launch_the_Softound_Url()"
            },
            "keyword": "When "
          },
          {
            "result": {
              "duration": 50936900,
              "status": "passed"
            },
            "line": 9,
            "name": "Enter the \"\"FirstName",
            "match": {
              "arguments": [
                {
                  "val": "\"\"",
                  "offset": 10
                }
              ],
              "location": "Chall.enter_the_FirstName(String)"
            },
            "keyword": "Then "
          },
          {
            "result": {
              "duration": 54084500,
              "status": "passed"
            },
            "line": 11,
            "name": "Enter the \"s\"LastName",
            "match": {
              "arguments": [
                {
                  "val": "\"s\"",
                  "offset": 10
                }
              ],
              "location": "Chall.enter_the_LastName(String)"
            },
            "keyword": "And "
          },
          {
            "result": {
              "duration": 58970300,
              "status": "passed"
            },
            "line": 13,
            "name": "Enter the \"12345\"EmailAddress",
            "match": {
              "arguments": [
                {
                  "val": "\"12345\"",
                  "offset": 10
                }
              ],
              "location": "Chall.enter_the_EmailAddress(String)"
            },
            "keyword": "And "
          },
          {
            "result": {
              "duration": 559186600,
              "status": "passed"
            },
            "line": 15,
            "name": "select Your \"29.05.2013\"BirthDate",
            "match": {
              "arguments": [
                {
                  "val": "\"29.05.2013\"",
                  "offset": 12
                }
              ],
              "location": "Chall.select_Your_BirthDate(String)"
            },
            "keyword": "And "
          },
          {
            "result": {
              "duration": 336543300,
              "status": "passed"
            },
            "line": 17,
            "name": "click SubmitButton",
            "match": {
              "location": "Chall.click_SubmitButton()"
            },
            "keyword": "And "
          },
          {
            "result": {
              "duration": 32571200,
              "status": "passed"
            },
            "line": 19,
            "name": "Print The Submission Message",
            "match": {
              "location": "Chall.print_The_Submission_Message()"
            },
            "keyword": "And "
          },
          {
            "result": {
              "duration": 3084446400,
              "status": "passed"
            },
            "line": 21,
            "name": "close the Browser",
            "match": {
              "location": "Chall.close_the_Browser()"
            },
            "keyword": "Then "
          }
        ]
      },
      {
        "line": 33,
        "name": "To Validate the Registration Form",
        "description": "",
        "id": "to-validate-the-softound-challenge;to-validate-the-registration-form;;10",
        "type": "scenario",
        "keyword": "Scenario Outline",
        "steps": [
          {
            "result": {
              "duration": 849182200,
              "status": "passed"
            },
            "line": 5,
            "name": ": launch the browser",
            "match": {
              "location": "Chall.launch_the_browser()"
            },
            "keyword": "Given "
          },
          {
            "result": {
              "duration": 3035492400,
              "status": "passed"
            },
            "line": 7,
            "name": "launch the Softound Url",
            "match": {
              "location": "Chall.launch_the_Softound_Url()"
            },
            "keyword": "When "
          },
          {
            "result": {
              "duration": 69777800,
              "status": "passed"
            },
            "line": 9,
            "name": "Enter the \"Jayapriya\"FirstName",
            "match": {
              "arguments": [
                {
                  "val": "\"Jayapriya\"",
                  "offset": 10
                }
              ],
              "location": "Chall.enter_the_FirstName(String)"
            },
            "keyword": "Then "
          },
          {
            "result": {
              "duration": 53604900,
              "status": "passed"
            },
            "line": 11,
            "name": "Enter the \"\"LastName",
            "match": {
              "arguments": [
                {
                  "val": "\"\"",
                  "offset": 10
                }
              ],
              "location": "Chall.enter_the_LastName(String)"
            },
            "keyword": "And "
          },
          {
            "result": {
              "duration": 74443200,
              "status": "passed"
            },
            "line": 13,
            "name": "Enter the \"sr.jpriya@gmail.com\"EmailAddress",
            "match": {
              "arguments": [
                {
                  "val": "\"sr.jpriya@gmail.com\"",
                  "offset": 10
                }
              ],
              "location": "Chall.enter_the_EmailAddress(String)"
            },
            "keyword": "And "
          },
          {
            "result": {
              "duration": 554624400,
              "status": "passed"
            },
            "line": 15,
            "name": "select Your \"50.05.1000\"BirthDate",
            "match": {
              "arguments": [
                {
                  "val": "\"50.05.1000\"",
                  "offset": 12
                }
              ],
              "location": "Chall.select_Your_BirthDate(String)"
            },
            "keyword": "And "
          },
          {
            "result": {
              "duration": 378859300,
              "status": "passed"
            },
            "line": 17,
            "name": "click SubmitButton",
            "match": {
              "location": "Chall.click_SubmitButton()"
            },
            "keyword": "And "
          },
          {
            "result": {
              "duration": 36037300,
              "status": "passed"
            },
            "line": 19,
            "name": "Print The Submission Message",
            "match": {
              "location": "Chall.print_The_Submission_Message()"
            },
            "keyword": "And "
          },
          {
            "result": {
              "duration": 3133411200,
              "status": "passed"
            },
            "line": 21,
            "name": "close the Browser",
            "match": {
              "location": "Chall.close_the_Browser()"
            },
            "keyword": "Then "
          }
        ]
      },
      {
        "line": 34,
        "name": "To Validate the Registration Form",
        "description": "",
        "id": "to-validate-the-softound-challenge;to-validate-the-registration-form;;11",
        "type": "scenario",
        "keyword": "Scenario Outline",
        "steps": [
          {
            "result": {
              "duration": 855279600,
              "status": "passed"
            },
            "line": 5,
            "name": ": launch the browser",
            "match": {
              "location": "Chall.launch_the_browser()"
            },
            "keyword": "Given "
          },
          {
            "result": {
              "duration": 2472996800,
              "status": "passed"
            },
            "line": 7,
            "name": "launch the Softound Url",
            "match": {
              "location": "Chall.launch_the_Softound_Url()"
            },
            "keyword": "When "
          },
          {
            "result": {
              "duration": 66867500,
              "status": "passed"
            },
            "line": 9,
            "name": "Enter the \"123987\"FirstName",
            "match": {
              "arguments": [
                {
                  "val": "\"123987\"",
                  "offset": 10
                }
              ],
              "location": "Chall.enter_the_FirstName(String)"
            },
            "keyword": "Then "
          },
          {
            "result": {
              "duration": 53256900,
              "status": "passed"
            },
            "line": 11,
            "name": "Enter the \"s\"LastName",
            "match": {
              "arguments": [
                {
                  "val": "\"s\"",
                  "offset": 10
                }
              ],
              "location": "Chall.enter_the_LastName(String)"
            },
            "keyword": "And "
          },
          {
            "result": {
              "duration": 51553400,
              "status": "passed"
            },
            "line": 13,
            "name": "Enter the \"\"EmailAddress",
            "match": {
              "arguments": [
                {
                  "val": "\"\"",
                  "offset": 10
                }
              ],
              "location": "Chall.enter_the_EmailAddress(String)"
            },
            "keyword": "And "
          },
          {
            "result": {
              "duration": 556592100,
              "status": "passed"
            },
            "line": 15,
            "name": "select Your \"29.15.1993\"BirthDate",
            "match": {
              "arguments": [
                {
                  "val": "\"29.15.1993\"",
                  "offset": 12
                }
              ],
              "location": "Chall.select_Your_BirthDate(String)"
            },
            "keyword": "And "
          },
          {
            "result": {
              "duration": 295181600,
              "status": "passed"
            },
            "line": 17,
            "name": "click SubmitButton",
            "match": {
              "location": "Chall.click_SubmitButton()"
            },
            "keyword": "And "
          },
          {
            "result": {
              "duration": 35123600,
              "status": "passed"
            },
            "line": 19,
            "name": "Print The Submission Message",
            "match": {
              "location": "Chall.print_The_Submission_Message()"
            },
            "keyword": "And "
          },
          {
            "result": {
              "duration": 3098604700,
              "status": "passed"
            },
            "line": 21,
            "name": "close the Browser",
            "match": {
              "location": "Chall.close_the_Browser()"
            },
            "keyword": "Then "
          }
        ]
      },
      {
        "line": 35,
        "name": "To Validate the Registration Form",
        "description": "",
        "id": "to-validate-the-softound-challenge;to-validate-the-registration-form;;12",
        "type": "scenario",
        "keyword": "Scenario Outline",
        "steps": [
          {
            "result": {
              "duration": 872806500,
              "status": "passed"
            },
            "line": 5,
            "name": ": launch the browser",
            "match": {
              "location": "Chall.launch_the_browser()"
            },
            "keyword": "Given "
          },
          {
            "result": {
              "duration": 3166360500,
              "status": "passed"
            },
            "line": 7,
            "name": "launch the Softound Url",
            "match": {
              "location": "Chall.launch_the_Softound_Url()"
            },
            "keyword": "When "
          },
          {
            "result": {
              "duration": 68417600,
              "status": "passed"
            },
            "line": 9,
            "name": "Enter the \"Jayapriya\"FirstName",
            "match": {
              "arguments": [
                {
                  "val": "\"Jayapriya\"",
                  "offset": 10
                }
              ],
              "location": "Chall.enter_the_FirstName(String)"
            },
            "keyword": "Then "
          },
          {
            "result": {
              "duration": 51521900,
              "status": "passed"
            },
            "line": 11,
            "name": "Enter the \"s\"LastName",
            "match": {
              "arguments": [
                {
                  "val": "\"s\"",
                  "offset": 10
                }
              ],
              "location": "Chall.enter_the_LastName(String)"
            },
            "keyword": "And "
          },
          {
            "result": {
              "duration": 74002500,
              "status": "passed"
            },
            "line": 13,
            "name": "Enter the \"sr.jpriya@gmail.com\"EmailAddress",
            "match": {
              "arguments": [
                {
                  "val": "\"sr.jpriya@gmail.com\"",
                  "offset": 10
                }
              ],
              "location": "Chall.enter_the_EmailAddress(String)"
            },
            "keyword": "And "
          },
          {
            "result": {
              "duration": 546214600,
              "status": "passed"
            },
            "line": 15,
            "name": "select Your \"\"BirthDate",
            "match": {
              "arguments": [
                {
                  "val": "\"\"",
                  "offset": 12
                }
              ],
              "location": "Chall.select_Your_BirthDate(String)"
            },
            "keyword": "And "
          },
          {
            "result": {
              "duration": 903932400,
              "status": "passed"
            },
            "line": 17,
            "name": "click SubmitButton",
            "match": {
              "location": "Chall.click_SubmitButton()"
            },
            "keyword": "And "
          },
          {
            "result": {
              "duration": 26934200,
              "status": "passed"
            },
            "line": 19,
            "name": "Print The Submission Message",
            "match": {
              "location": "Chall.print_The_Submission_Message()"
            },
            "keyword": "And "
          },
          {
            "result": {
              "duration": 3095124500,
              "status": "passed"
            },
            "line": 21,
            "name": "close the Browser",
            "match": {
              "location": "Chall.close_the_Browser()"
            },
            "keyword": "Then "
          }
        ]
      },
      {
        "line": 36,
        "name": "To Validate the Registration Form",
        "description": "",
        "id": "to-validate-the-softound-challenge;to-validate-the-registration-form;;13",
        "type": "scenario",
        "keyword": "Scenario Outline",
        "steps": [
          {
            "result": {
              "duration": 782944400,
              "status": "passed"
            },
            "line": 5,
            "name": ": launch the browser",
            "match": {
              "location": "Chall.launch_the_browser()"
            },
            "keyword": "Given "
          },
          {
            "result": {
              "duration": 2220918000,
              "status": "passed"
            },
            "line": 7,
            "name": "launch the Softound Url",
            "match": {
              "location": "Chall.launch_the_Softound_Url()"
            },
            "keyword": "When "
          },
          {
            "result": {
              "duration": 52011100,
              "status": "passed"
            },
            "line": 9,
            "name": "Enter the \"\"FirstName",
            "match": {
              "arguments": [
                {
                  "val": "\"\"",
                  "offset": 10
                }
              ],
              "location": "Chall.enter_the_FirstName(String)"
            },
            "keyword": "Then "
          },
          {
            "result": {
              "duration": 54063800,
              "status": "passed"
            },
            "line": 11,
            "name": "Enter the \"s\"LastName",
            "match": {
              "arguments": [
                {
                  "val": "\"s\"",
                  "offset": 10
                }
              ],
              "location": "Chall.enter_the_LastName(String)"
            },
            "keyword": "And "
          },
          {
            "result": {
              "duration": 59425700,
              "status": "passed"
            },
            "line": 13,
            "name": "Enter the \"\"EmailAddress",
            "match": {
              "arguments": [
                {
                  "val": "\"\"",
                  "offset": 10
                }
              ],
              "location": "Chall.enter_the_EmailAddress(String)"
            },
            "keyword": "And "
          },
          {
            "result": {
              "duration": 553211700,
              "status": "passed"
            },
            "line": 15,
            "name": "select Your \"29.05.2013\"BirthDate",
            "match": {
              "arguments": [
                {
                  "val": "\"29.05.2013\"",
                  "offset": 12
                }
              ],
              "location": "Chall.select_Your_BirthDate(String)"
            },
            "keyword": "And "
          },
          {
            "result": {
              "duration": 223855900,
              "status": "passed"
            },
            "line": 17,
            "name": "click SubmitButton",
            "match": {
              "location": "Chall.click_SubmitButton()"
            },
            "keyword": "And "
          },
          {
            "result": {
              "duration": 35793600,
              "status": "passed"
            },
            "line": 19,
            "name": "Print The Submission Message",
            "match": {
              "location": "Chall.print_The_Submission_Message()"
            },
            "keyword": "And "
          },
          {
            "result": {
              "duration": 3100888900,
              "status": "passed"
            },
            "line": 21,
            "name": "close the Browser",
            "match": {
              "location": "Chall.close_the_Browser()"
            },
            "keyword": "Then "
          }
        ]
      },
      {
        "line": 37,
        "name": "To Validate the Registration Form",
        "description": "",
        "id": "to-validate-the-softound-challenge;to-validate-the-registration-form;;14",
        "type": "scenario",
        "keyword": "Scenario Outline",
        "steps": [
          {
            "result": {
              "duration": 783624100,
              "status": "passed"
            },
            "line": 5,
            "name": ": launch the browser",
            "match": {
              "location": "Chall.launch_the_browser()"
            },
            "keyword": "Given "
          },
          {
            "result": {
              "duration": 2881937100,
              "status": "passed"
            },
            "line": 7,
            "name": "launch the Softound Url",
            "match": {
              "location": "Chall.launch_the_Softound_Url()"
            },
            "keyword": "When "
          },
          {
            "result": {
              "duration": 69713500,
              "status": "passed"
            },
            "line": 9,
            "name": "Enter the \"Jayapriya\"FirstName",
            "match": {
              "arguments": [
                {
                  "val": "\"Jayapriya\"",
                  "offset": 10
                }
              ],
              "location": "Chall.enter_the_FirstName(String)"
            },
            "keyword": "Then "
          },
          {
            "result": {
              "duration": 50000200,
              "status": "passed"
            },
            "line": 11,
            "name": "Enter the \"\"LastName",
            "match": {
              "arguments": [
                {
                  "val": "\"\"",
                  "offset": 10
                }
              ],
              "location": "Chall.enter_the_LastName(String)"
            },
            "keyword": "And "
          },
          {
            "result": {
              "duration": 70453800,
              "status": "passed"
            },
            "line": 13,
            "name": "Enter the \"sr.jpriya@gmail.com\"EmailAddress",
            "match": {
              "arguments": [
                {
                  "val": "\"sr.jpriya@gmail.com\"",
                  "offset": 10
                }
              ],
              "location": "Chall.enter_the_EmailAddress(String)"
            },
            "keyword": "And "
          },
          {
            "result": {
              "duration": 547898200,
              "status": "passed"
            },
            "line": 15,
            "name": "select Your \"\"BirthDate",
            "match": {
              "arguments": [
                {
                  "val": "\"\"",
                  "offset": 12
                }
              ],
              "location": "Chall.select_Your_BirthDate(String)"
            },
            "keyword": "And "
          },
          {
            "result": {
              "duration": 321634100,
              "status": "passed"
            },
            "line": 17,
            "name": "click SubmitButton",
            "match": {
              "location": "Chall.click_SubmitButton()"
            },
            "keyword": "And "
          },
          {
            "result": {
              "duration": 34195500,
              "status": "passed"
            },
            "line": 19,
            "name": "Print The Submission Message",
            "match": {
              "location": "Chall.print_The_Submission_Message()"
            },
            "keyword": "And "
          },
          {
            "result": {
              "duration": 3087595500,
              "status": "passed"
            },
            "line": 21,
            "name": "close the Browser",
            "match": {
              "location": "Chall.close_the_Browser()"
            },
            "keyword": "Then "
          }
        ]
      },
      {
        "line": 38,
        "name": "To Validate the Registration Form",
        "description": "",
        "id": "to-validate-the-softound-challenge;to-validate-the-registration-form;;15",
        "type": "scenario",
        "keyword": "Scenario Outline",
        "steps": [
          {
            "result": {
              "duration": 840860500,
              "status": "passed"
            },
            "line": 5,
            "name": ": launch the browser",
            "match": {
              "location": "Chall.launch_the_browser()"
            },
            "keyword": "Given "
          },
          {
            "result": {
              "duration": 2556569900,
              "status": "passed"
            },
            "line": 7,
            "name": "launch the Softound Url",
            "match": {
              "location": "Chall.launch_the_Softound_Url()"
            },
            "keyword": "When "
          },
          {
            "result": {
              "duration": 55312200,
              "status": "passed"
            },
            "line": 9,
            "name": "Enter the \"\"FirstName",
            "match": {
              "arguments": [
                {
                  "val": "\"\"",
                  "offset": 10
                }
              ],
              "location": "Chall.enter_the_FirstName(String)"
            },
            "keyword": "Then "
          },
          {
            "result": {
              "duration": 57623100,
              "status": "passed"
            },
            "line": 11,
            "name": "Enter the \"s\"LastName",
            "match": {
              "arguments": [
                {
                  "val": "\"s\"",
                  "offset": 10
                }
              ],
              "location": "Chall.enter_the_LastName(String)"
            },
            "keyword": "And "
          },
          {
            "result": {
              "duration": 69637700,
              "status": "passed"
            },
            "line": 13,
            "name": "Enter the \"sr.jpriya@gmail.com\"EmailAddress",
            "match": {
              "arguments": [
                {
                  "val": "\"sr.jpriya@gmail.com\"",
                  "offset": 10
                }
              ],
              "location": "Chall.enter_the_EmailAddress(String)"
            },
            "keyword": "And "
          },
          {
            "result": {
              "duration": 557035900,
              "status": "passed"
            },
            "line": 15,
            "name": "select Your \"29.15.1993\"BirthDate",
            "match": {
              "arguments": [
                {
                  "val": "\"29.15.1993\"",
                  "offset": 12
                }
              ],
              "location": "Chall.select_Your_BirthDate(String)"
            },
            "keyword": "And "
          },
          {
            "result": {
              "duration": 239560600,
              "status": "passed"
            },
            "line": 17,
            "name": "click SubmitButton",
            "match": {
              "location": "Chall.click_SubmitButton()"
            },
            "keyword": "And "
          },
          {
            "result": {
              "duration": 35359200,
              "status": "passed"
            },
            "line": 19,
            "name": "Print The Submission Message",
            "match": {
              "location": "Chall.print_The_Submission_Message()"
            },
            "keyword": "And "
          },
          {
            "result": {
              "duration": 3129496900,
              "status": "passed"
            },
            "line": 21,
            "name": "close the Browser",
            "match": {
              "location": "Chall.close_the_Browser()"
            },
            "keyword": "Then "
          }
        ]
      }
    ],
    "name": "To Validate the Softound Challenge",
    "description": "",
    "id": "to-validate-the-softound-challenge",
    "keyword": "Feature",
    "uri": "src/test/resources/challenge.feature",
    "tags": []
  }
]